dtlpy_agent/__init__.py
dtlpy_agent/exceptions.py
dtlpy_agent/cli/__init__.py
dtlpy_agent/cli/agnt
dtlpy_agent/cli/agnt.bat
dtlpy_agent/cli/agnt.py
dtlpy_agent/cli/executor.py
dtlpy_agent/cli/parser.py
dtlpy_agent/cli/proxy_debug.py
dtlpy_agent/cli/runner_debug.py
dtlpy_agent/proxy/__init__.py
dtlpy_agent/proxy/ampq_connection.py
dtlpy_agent/proxy/ampq_connection_publisher.py
dtlpy_agent/proxy/bootstraper.py
dtlpy_agent/proxy/execution_monitor.py
dtlpy_agent/proxy/local_server.py
dtlpy_agent/proxy/proxy.py
dtlpy_agent/proxy/runner_heartbeat.py
dtlpy_agent/proxy/usage.py
dtlpy_agent/runner/__init__.py
dtlpy_agent/runner/directory_sync.py
dtlpy_agent/runner/gitUtils.py
dtlpy_agent/runner/progress.py
dtlpy_agent/runner/runner.py
dtlpy_agent/runner/runner_local_server.py
dtlpy_agent/runner/usage.py
dtlpy_agent/services/__init__.py
dtlpy_agent/services/client_api.py
dtlpy_agent/services/io_handler.py
dtlpy_agent/services/prometheus_metrics.py
dtlpy_agent/services/redirect.py
dtlpy_agent/services/requests_session.py
dtlpy_agent/services/termination_handlers.py
dtlpy_agent/services/web_socket.py
dtlpy_agent-1.58.29.0.data/scripts/agnt
dtlpy_agent-1.58.29.0.data/scripts/agnt.bat
dtlpy_agent-1.58.29.0.data/scripts/agnt.py
tests/__init__.py
tests/context.py
tests/env_from_git_branch.py
tests/test_login.py
tests/test_runner.py
tests/features/__init__.py
tests/features/environment.py
dtlpy_agent-1.58.29.0.dist-info/LICENSE
dtlpy_agent-1.58.29.0.dist-info/METADATA
dtlpy_agent-1.58.29.0.dist-info/WHEEL
dtlpy_agent-1.58.29.0.dist-info/entry_points.txt
dtlpy_agent-1.58.29.0.dist-info/top_level.txt
dtlpy_agent-1.58.29.0.dist-info/RECORD
