Metadata-Version: 2.1
Name: dtlpy-agent
Version: 1.58.29.0
Summary: Dataloop package runner
Home-page: https://github.com/dataloop-ai/dtlpy
Author: Or Shabtay
Author-email: or@dataloop.ai
License: Apache License 2.0
Platform: UNKNOWN
Requires-Python: >=3.5
Requires-Dist: amqpstorm (<=2.9.0)
Requires-Dist: PyJWT (<2.0.0,>=1.7.1)
Requires-Dist: psutil (<=5.8.0)
Requires-Dist: tornado (==6.0.2)
Requires-Dist: requests (<=2.26.0)
Requires-Dist: bump2version (==0.5.10)
Requires-Dist: bumpversion (==0.5.3)
Requires-Dist: prometheus-client (==0.7.1)
Requires-Dist: redis (==3.5.3)
Requires-Dist: websocket-client (==1.2.3)
